mitta_mistralai/__init__.py
mitta_mistralai/async_client.py
mitta_mistralai/client.py
mitta_mistralai/client_base.py
mitta_mistralai/constants.py
mitta_mistralai/exceptions.py
mitta_mistralai/models/__init__.py
mitta_mistralai/models/chat_completion.py
mitta_mistralai/models/common.py
mitta_mistralai/models/embeddings.py
mitta_mistralai/models/models.py
mitta_mistralai/py.typed
mitta_mistralai-0.1.3b2.dist-info/LICENSE
mitta_mistralai-0.1.3b2.dist-info/METADATA
mitta_mistralai-0.1.3b2.dist-info/WHEEL
mitta_mistralai-0.1.3b2.dist-info/RECORD
