Metadata-Version: 2.1
Name: mitta_mistralai
Version: 0.1.3b2
Summary: Fork of MistralAI client library with httpx allowed to be 0.27.0+. Will track with official Mistral release until this is addressed in the main package.
Author: Kord Campbell
Author-email: kordless@gmail.com
Requires-Python: >=3.9,<4.0
Classifier: Programming Language :: Python :: 3
Classifier: Programming Language :: Python :: 3.9
Classifier: Programming Language :: Python :: 3.10
Classifier: Programming Language :: Python :: 3.11
Classifier: Programming Language :: Python :: 3.12
Requires-Dist: httpx (>=0.27.0,<0.28.0)
Requires-Dist: orjson (>=3.9.10,<4.0.0)
Requires-Dist: pandas (>=2.2.0,<3.0.0)
Requires-Dist: pyarrow (>=15.0.0,<16.0.0)
Requires-Dist: pydantic (>=2.5.2,<3.0.0)
